MANIFEST.in
README.md
setup.cfg
setup.py
pythonWordArt/__init__.py
pythonWordArt/main.py
pythonWordArt.egg-info/PKG-INFO
pythonWordArt.egg-info/SOURCES.txt
pythonWordArt.egg-info/dependency_links.txt
pythonWordArt.egg-info/requires.txt
pythonWordArt.egg-info/top_level.txt
pythonWordArt/css3wordart/.gitignore
pythonWordArt/css3wordart/README.md
pythonWordArt/css3wordart/index.html
pythonWordArt/css3wordart/css/style.css
pythonWordArt/css3wordart/css/fonts/MicrosoftSansSerif.eot
pythonWordArt/css3wordart/css/fonts/MicrosoftSansSerif.svg
pythonWordArt/css3wordart/css/fonts/MicrosoftSansSerif.ttf
pythonWordArt/css3wordart/css/fonts/MicrosoftSansSerif.woff
pythonWordArt/css3wordart/js/object-observe-lite.js
pythonWordArt/css3wordart/js/wordart.js